langmanager.py
langmanager-1.4.2.dist-info/LICENSE
langmanager-1.4.2.dist-info/WHEEL
langmanager-1.4.2.dist-info/METADATA
langmanager-1.4.2.dist-info/RECORD
