Metadata-Version: 2.1
Name: langmanager
Version: 1.4.2
Summary: this library allows you to create translations of projects into other languages
Home-page: https://github.com/ASVIEST/LangManager
Keywords: lang,langmanager,langs,translate,language,languages,localization
Author: ASVI
Author-email: aaaaaabbbbbbccscc@gmail.com
Requires-Python: >=3.1,<4.0
Classifier: Programming Language :: Python :: 3
Classifier: Programming Language :: Python :: 3.4
Classifier: Programming Language :: Python :: 3.5
Classifier: Programming Language :: Python :: 3.6
Classifier: Programming Language :: Python :: 3.7
Classifier: Programming Language :: Python :: 3.8
Project-URL: Repository, https://github.com/ASVIEST/LangManager
